{
  "pages": [
    {
      "headings": {
        "cs3281%262---2019-batch": "CS3281&amp;2 - 2019 Batch",
        "markbind": "MarkBind",
        "chin-kun-song%2C-marvin": "CHIN KUN SONG, MARVIN",
        "lu-yang-kenneth": "LU YANG KENNETH",
        "maddi-aadyaa": "MADDI AADYAA",
        "tan-zhen-yong": "TAN ZHEN YONG",
        "powerpointlabs": "PowerPointLabs",
        "bryan-lew-ju-yu": "BRYAN LEW JU YU",
        "sng-yu-feng-chester": "SNG YU FENG CHESTER",
        "yu-pei-henry": "YU PEI HENRY",
        "reposense": "RepoSense",
        "chelsey-ong-hee": "CHELSEY ONG HEE",
        "gilbert-emerson": "GILBERT EMERSON",
        "lin-si-jie": "LIN SI JIE",
        "ong-shu-peng": "ONG SHU PENG",
        "wang-chao": "WANG CHAO",
        "teammates": "TEAMMATES",
        "amrut-prabhu": "AMRUT PRABHU",
        "chattoraj-ayush": "CHATTORAJ AYUSH",
        "jeremy-choo-wun-ka": "JEREMY CHOO WUN KA",
        "jiang-chunhui": "JIANG CHUNHUI",
        "li-pengcheng": "LI PENGCHENG",
        "monika-manuela-hengki": "MONIKA MANUELA HENGKI",
        "rahul-rajesh": "RAHUL RAJESH",
        "ronak-lakhotia": "RONAK LAKHOTIA",
        "tan-heng-yeow": "TAN HENG YEOW",
        "wang-junming": "WANG JUNMING"
      },
      "title": "CS3281&2 - 2019 Batch",
      "src": "index.mbd",
      "layout": "default"
    },
    {
      "headings": {
        "general-instructions-for-adding-to-this-repo": "General Instructions for adding to this Repo",
        "updating-the-student-list": "Updating the Student List",
        "adding-the-resume": "Adding the Resume",
        "updating-your-project-progress": "Updating your Project Progress",
        "updating-the-process-observations-page": "Updating the Process Observations Page"
      },
      "src": "instructions.mbd",
      "title": "",
      "layout": "default"
    }
  ]
}
